Workbook
Name Aporte: App!$D$18
Name Patrimonio_Total: App!$D$21
Name QTDE_Anos: App!$D$19
Name Rendimento_Carteira: App!$D$14
Name Salario: App!$D$13
Name Sugestao: App!$D$15
Name Taxa_Mensal: App!$D$20

Sheet App
B12: Configurações
B13: Salário | D13: 5554.46
B14: Rendimento Carteira | D14: 0.0102
B15: Sugestão de Investimento | D15: =D13*10% -> 555.446
B17: Investimento Mensal
B18: Quanto investir por mês? | D18: 500
B19: Por quantos anos? | D19: 8
B20: Taxa de rendimento mensal? | D20: 0.0108
B21: Patrimônio acumulado? | D21: =FV(Taxa_Mensal,QTDE_Anos*12,Aporte*-1) -> 83543.744
B22: Dividendos mensais? | D22: =Patrimonio_Total*Rendimento_Carteira -> 852.14619
B24: Cenários | D24: Dividendos
A25: 2 | B25: Quanto em 2 Anos? | C25: =FV(Taxa_Mensal,A25*12,Aporte*-1) -> 13615.432 | D25: =C25*Rendimento_Carteira -> 138.8774
A26: 5 | B26: Quanto em 5 Anos? | C26: =FV(Taxa_Mensal,A26*12,Aporte*-1) -> 41902.01 | D26: =C26*Rendimento_Carteira -> 427.4005
A27: 10 | B27: Quanto em 10 Anos? | C27: =FV(Taxa_Mensal,A27*12,Aporte*-1) -> 121728.83 | D27: =C27*Rendimento_Carteira -> 1241.6341
A28: 20 | B28: Quanto em 20 Anos? | C28: =FV(Taxa_Mensal,A28*12,Aporte*-1) -> 563524.5 | D28: =C28*Rendimento_Carteira -> 5747.9499
A29: 30 | B29: Quanto em 30 Anos? | C29: =FV(Taxa_Mensal,A29*12,Aporte*-1) -> 2166952.4 | D29: =C29*Rendimento_Carteira -> 22102.915
A30: 35 | B30: Quanto em 35 Anos? | C30: =FV(Taxa_Mensal,A30*12,Aporte*-1) -> 4170127.1 | D30: =C30*Rendimento_Carteira -> 42535.296
B32: Perfil | C32: Conservador
B33: Valor a ser investido por mês | C33: =Aporte -> 500
B35: Tipos de FII | C35: Percentual Sugerido | D35: Valores
B36: Papel | C36: =_xlfn.XLOOKUP($C$32&"-"&B36,Apoio!A:A,Apoio!D:D) -> 0.3 | D36: =C36*$C$33 -> 150
B37: Tijolo | C37: =_xlfn.XLOOKUP($C$32&"-"&B37,Apoio!A:A,Apoio!D:D) -> 0.5 | D37: =C37*$C$33 -> 250
B38: Hibridos | C38: =_xlfn.XLOOKUP($C$32&"-"&B38,Apoio!A:A,Apoio!D:D) -> 0.1 | D38: =C38*$C$33 -> 50
B39: FOFs | C39: =_xlfn.XLOOKUP($C$32&"-"&B39,Apoio!A:A,Apoio!D:D) -> 0.1 | D39: =C39*$C$33 -> 50
B40: Desenvolvimento | C40: =_xlfn.XLOOKUP($C$32&"-"&B40,Apoio!A:A,Apoio!D:D) -> 0 | D40: =C40*$C$33 -> 0
B41: Hotelarias | C41: =_xlfn.XLOOKUP($C$32&"-"&B41,Apoio!A:A,Apoio!D:D) -> 0 | D41: =C41*$C$33 -> 0
D42: =SUM(D36:D41) -> 500

Sheet Apoio
A1: Chave | B1: Perfil | C1: Tipo de FII | D1: %
A2: =B2&"-"&C2 -> Conservador-Papel | B2: Conservador | C2: Papel | D2: 0.3
A3: =B3&"-"&C3 -> Conservador-Tijolo | B3: Conservador | C3: Tijolo | D3: 0.5
A4: =B4&"-"&C4 -> Conservador-Hibridos | B4: Conservador | C4: Hibridos | D4: 0.1
A5: =B5&"-"&C5 -> Conservador-FOFs | B5: Conservador | C5: FOFs | D5: 0.1
A6: =B6&"-"&C6 -> Conservador-Desenvolvimento | B6: Conservador | C6: Desenvolvimento | D6: 0
A7: =B7&"-"&C7 -> Conservador-Hotelarias | B7: Conservador | C7: Hotelarias | D7: 0
A8: =B8&"-"&C8 -> Moderado-Papel | B8: Moderado | C8: Papel | D8: 0.32
A9: =B9&"-"&C9 -> Moderado-Tijolo | B9: Moderado | C9: Tijolo | D9: 0.4
A10: =B10&"-"&C10 -> Moderado-Hibridos | B10: Moderado | C10: Hibridos | D10: 0.08
A11: =B11&"-"&C11 -> Moderado-FOFs | B11: Moderado | C11: FOFs | D11: 0.1
A12: =B12&"-"&C12 -> Moderado-Desenvolvimento | B12: Moderado | C12: Desenvolvimento | D12: 0.05
A13: =B13&"-"&C13 -> Moderado-Hotelarias | B13: Moderado | C13: Hotelarias | D13: 0.05
... A19: =B19&"-"&C19 -> Agressivo-Hotelarias | B19: Agressivo | C19: Hotelarias | D19: 0.1
